README.txt
setup.py
brining/__init__.py
brining.egg-info/PKG-INFO
brining.egg-info/SOURCES.txt
brining.egg-info/dependency_links.txt
brining.egg-info/requires.txt
brining.egg-info/top_level.txt
brining/tests/__init__.py
brining/tests/testBrine.py
brining/tests/testBrined.py
brining/tests/testDebrine.py