Metadata-Version: 1.0
Name: brining
Version: 0.2.5
Summary: Python object to/from JSON serialization/deserialization module
Home-page: https://github.com/SmithSamuelM/brine
Author: Samuel M Smith
Author-email: smith.samuel.m@gmail.com
License: MIT
Keywords: Python object JSON serialization
Platform: UNKNOWN
